riot_games_api/__init__.py
riot_games_api/account.py
riot_games_api/api.py
riot_games_api/base.py
riot_games_api/champion.py
riot_games_api/champion_mastery.py
riot_games_api/clash.py
riot_games_api/context.py
riot_games_api/exceptions.py
riot_games_api/league.py
riot_games_api/league_exp.py
riot_games_api/lol_status.py
riot_games_api/match.py
riot_games_api/spectator.py
riot_games_api/summoner.py
riot_games_api/models/__init__.py
riot_games_api/models/account.py
riot_games_api/models/base.py
riot_games_api/models/champion.py
riot_games_api/models/champion_mastery.py
riot_games_api/models/clash.py
riot_games_api/models/league.py
riot_games_api/models/lol_status.py
riot_games_api/models/match.py
riot_games_api/models/spectator.py
riot_games_api/models/summoner.py
riot_games_api-1.0.3.dist-info/LICENSE
riot_games_api-1.0.3.dist-info/METADATA
riot_games_api-1.0.3.dist-info/WHEEL
riot_games_api-1.0.3.dist-info/top_level.txt
riot_games_api-1.0.3.dist-info/RECORD
